{
  "validators": [
    {
      "userId": "SPV001",
      "userPw": "test1",
      "userName": "Oliver Roberts",
      "inSession": false,
      "id": 1
    },
    {
      "userId": "SPV002",
      "userPw": "test2",
      "userName": "Arnoldo Nielsen",
      "inSession": false,
      "id": 2
    },
    {
      "userId": "SPV003",
      "userPw": "test3",
      "userName": "Tyrone Ingram",
      "inSession": false,
      "id": 3
    },
    {
      "userId": "SPV004",
      "userPw": "test4",
      "userName": "Verda Kinsman",
      "inSession": false,
      "id": 4
    },
    {
      "userId": "SPV005",
      "userPw": "test5",
      "userName": "Esmond Dickinson",
      "inSession": false,
      "id": 5
    }
  ],
  "ptw": [
    {
      "ptwId": "PTW-230001",
      "ptwYear": "2023",
      "locationOfWork": {
        "main": "Biodiesel production sector",
        "sub": "Biodiesel purification"
      },
      "permitType": "Cold work permit (CWP)",
      "startWorkingDateTime": "2023-06-01T00:30:00.000Z",
      "endWorkingDateTime": "2023-06-10T07:00:00.000Z",
      "predefinedTask": "Others",
      "predefinedTaskOthers": "temp testing",
      "noOfWorkers": 2,
      "noOfSupervisors": 2,
      "workAtHeight": {
        "sectionOne": {
          "controlMeasuresImplemented": {
            "q01": {
              "choice": "None",
              "remarks": "None"
            },
            "q02": {
              "choice": "None",
              "remarks": "None"
            },
            "q03": {
              "choice": "None",
              "remarks": "None"
            },
            "q04": {
              "choice": "None",
              "remarks": "None"
            },
            "q05": {
              "choice": "None",
              "remarks": "None"
            },
            "q06": {
              "choice": "None",
              "remarks": "None"
            },
            "q07": {
              "choice": "None",
              "remarks": "None"
            },
            "q08": {
              "choice": "None",
              "remarks": "None"
            },
            "q09": {
              "choice": "None",
              "remarks": "None"
            },
            "q10": {
              "choice": "None",
              "remarks": "None"
            },
            "q11": {
              "specify": "None"
            }
          }
        },
        "sectionTwo": {
          "assessmentOfControlMeasures": {
            "q01": {
              "choice": "None",
              "remarks": "None"
            },
            "q02": {
              "choice": "None",
              "remarks": "None"
            }
          },
          "siteSurveyFromSupervisor": {
            "q01": {
              "choice": "None",
              "remarks": "None"
            },
            "q02": {
              "choice": "None",
              "remarks": "None"
            }
          },
          "multiLocOrExtentedDuration": {
            "q01": {
              "choice": "None",
              "remarks": "None"
            },
            "q02": {
              "choice": "None",
              "remarks": "None"
            }
          }
        },
        "sectionThree": {
          "permitReview": {
            "q01": {
              "choice": "None",
              "remarks": "None"
            },
            "q02": {
              "choice": "None",
              "remarks": "None"
            },
            "q03": {
              "choice": "None",
              "remarks": "None"
            },
            "q04": {
              "choice": "None",
              "remarks": "None"
            }
          }
        }
      },
      "confinedSpace": {
        "sectionOne": {
          "potentialHazards": {
            "atmo": "None",
            "nonAtmo": "None"
          },
          "controlMeasuresImplemented": {
            "preEntryReqs": {
              "q01": "None",
              "q02": "None",
              "q03": "None",
              "q04": "None",
              "q05": "None",
              "q06": "None",
              "q07": "None",
              "q08": "None"
            },
            "ppe": {
              "q01": "None",
              "q02": "None",
              "q03": "None",
              "q04": "None",
              "q05": "None",
              "q06": "None",
              "q07": {
                "specify": "None"
              }
            }
          }
        },
        "sectionTwo": {
          "gasMonitoringRes": {
            "oxygenLevel": 0,
            "flammableGasLevel": 0,
            "toxicGasLevel": 0,
            "fitForEntry": false
          }
        },
        "sectionThree": {
          "permitReview": {
            "q01": "None",
            "q02": "None",
            "q03": "None",
            "q04": "None"
          }
        }
      },
      "hotWork": {
        "sectionOne": {
          "controlMeasuresImplemented": {
            "q01": {
              "choice": "None",
              "remarks": "None"
            },
            "q02": {
              "choice": "None",
              "remarks": "None"
            },
            "q03": {
              "choice": "None",
              "remarks": "None"
            },
            "q04": {
              "choice": "None",
              "remarks": "None"
            },
            "q05": {
              "choice": "None",
              "remarks": "None"
            },
            "q06": {
              "choice": "None",
              "remarks": "None"
            },
            "q07": {
              "choice": "None",
              "remarks": "None"
            },
            "q08": {
              "choice": "None",
              "remarks": "None"
            },
            "q09": {
              "choice": "None",
              "remarks": "None"
            },
            "q10": {
              "choice": "None",
              "remarks": "None"
            },
            "q11": {
              "choice": "None",
              "remarks": "None"
            },
            "q12": {
              "specify": "None"
            },
            "q13": {
              "specify": "None"
            }
          }
        },
        "sectionTwo": {
          "assessment": {
            "q01": {
              "choice": "None",
              "remarks": "None"
            }
          }
        },
        "sectionThree": {
          "permitReview": {
            "q01": {
              "choice": "None",
              "remarks": "None"
            },
            "q02": {
              "choice": "None",
              "remarks": "None"
            },
            "q03": {
              "choice": "None",
              "remarks": "None"
            },
            "q04": {
              "choice": "None",
              "remarks": "None"
            }
          }
        }
      },
      "coldWork": {
        "sectionOne": {
          "controlMeasuresImplemented": {
            "q01": {
              "choice": "Yes",
              "remarks": "None"
            },
            "q02": {
              "choice": "No",
              "remarks": "None"
            },
            "q03": {
              "choice": "No",
              "remarks": "None"
            },
            "q04": {
              "choice": "Yes",
              "remarks": "None"
            },
            "q05": {
              "choice": "N/A",
              "remarks": "use a digital temp-meter"
            },
            "q06": {
              "choice": "No",
              "remarks": "None"
            },
            "q07": {
              "choice": "No",
              "remarks": "None"
            },
            "q08": {
              "choice": "No",
              "remarks": "None"
            },
            "q09": {
              "choice": "Yes",
              "remarks": "None"
            },
            "q10": {
              "specify": "wear temp protecter"
            },
            "q11": {
              "specify": "nothing"
            }
          }
        },
        "sectionTwo": {
          "assessment": {
            "q01": {
              "choice": "Yes",
              "remarks": "None"
            }
          }
        },
        "sectionThree": {
          "permitReview": {
            "q01": {
              "choice": "No",
              "remarks": "None"
            },
            "q02": {
              "choice": "Yes",
              "remarks": "None"
            },
            "q03": {
              "choice": "Yes",
              "remarks": "None"
            },
            "q04": {
              "choice": "No",
              "remarks": "None"
            }
          }
        }
      },
      "electrical": {
        "sectionOne": {
          "controlMeasuresImplemented": {
            "q01": {
              "choice": "None",
              "remarks": "None"
            },
            "q02": {
              "choice": "None",
              "remarks": "None"
            },
            "q03": {
              "choice": "None",
              "remarks": "None"
            },
            "q04": {
              "choice": "None",
              "remarks": "None"
            },
            "q05": {
              "choice": "None",
              "remarks": "None"
            },
            "q06": {
              "choice": "None",
              "remarks": "None"
            },
            "q07": {
              "choice": "None",
              "remarks": "None"
            },
            "q08": {
              "choice": "None",
              "remarks": "None"
            },
            "q09": {
              "choice": "None",
              "remarks": "None"
            },
            "q10": {
              "specify": "None"
            },
            "q11": {
              "specify": "None"
            }
          }
        },
        "sectionTwo": {
          "assessment": {
            "q01": {
              "choice": "None",
              "remarks": "None"
            }
          }
        },
        "sectionThree": {
          "permitReview": {
            "q01": {
              "choice": "None",
              "remarks": "None"
            },
            "q02": {
              "choice": "None",
              "remarks": "None"
            },
            "q03": {
              "choice": "None",
              "remarks": "None"
            },
            "q04": {
              "choice": "None",
              "remarks": "None"
            }
          }
        }
      },
      "attendantDets": [
        {
          "id": 1,
          "name": "Kenny",
          "nricOrFinNo": "H7676767G",
          "role": "Supervisor",
          "contactNo": "+65 3843-8754"
        },
        {
          "id": 2,
          "name": "Jason",
          "nricOrFinNo": "K4834785G",
          "role": "Supervisor",
          "contactNo": 43545665
        },
        {
          "id": 3,
          "name": "Lucas",
          "nricOrFinNo": "N4554746V",
          "role": "Worker",
          "contactNo": 4535353
        },
        {
          "id": 4,
          "name": "Harry",
          "nricOrFinNo": "F4565476E",
          "role": "Worker",
          "contactNo": 435242342
        },
        {
          "id": 5,
          "name": "None",
          "nricOrFinNo": "None",
          "role": "None",
          "contactNo": "None"
        },
        {
          "id": 6,
          "name": "None",
          "nricOrFinNo": "None",
          "role": "None",
          "contactNo": "None"
        }
      ],
      "applicantDets": {
        "name": "Kenny",
        "nricOrFinNo": "H7676767G",
        "orgType": "Internal",
        "orgName": "None",
        "depName": "Thermo Dept",
        "contactNo": "+65 3843-8754",
        "email": "kenny123@student.tp.edu.sg"
      },
      "ptwStatus": {
        "permitStatus": "Valid",
        "taskStatus": "Not Started",
        "remarks": "None",
        "checked": false,
        "supervisorName": "None",
        "wantToTerminate": false,
        "reqTermTimestamp": "None",
        "terminatedTimestamp": "None",
        "timestamp": "2023-06-01T02:36:28.650Z"
      },
      "safetyAssessorEvaluation": {
        "passed": true,
        "name": "Arnoldo Nielsen (SPV002)",
        "timestamp": "2023-06-01T02:34:50.532Z"
      },
      "authorisedManagerApproval": {
        "passed": true,
        "name": "Arnoldo Nielsen (SPV002)",
        "timestamp": "2023-06-01T02:36:28.650Z"
      },
      "requestStatus": "Approved",
      "wantToCancel": false,
      "reqCancTimestamp": "None",
      "cancelledTimestamp": "None",
      "timestamp": "2023-06-01T02:29:01.066Z",
      "id": 1
    },
    {
      "ptwId": "PTW-230002",
      "ptwYear": "2023",
      "locationOfWork": {
        "main": "Wastewater treatment sector",
        "sub": "Secondary treatment"
      },
      "permitType": "Electrical permit (EP)",
      "startWorkingDateTime": "2023-06-02T01:00:00.000Z",
      "endWorkingDateTime": "2023-06-08T08:30:00.000Z",
      "predefinedTask": "Preventive Maintenance",
      "predefinedTaskOthers": "",
      "noOfWorkers": 1,
      "noOfSupervisors": 1,
      "workAtHeight": {
        "sectionOne": {
          "controlMeasuresImplemented": {
            "q01": {
              "choice": "None",
              "remarks": "None"
            },
            "q02": {
              "choice": "None",
              "remarks": "None"
            },
            "q03": {
              "choice": "None",
              "remarks": "None"
            },
            "q04": {
              "choice": "None",
              "remarks": "None"
            },
            "q05": {
              "choice": "None",
              "remarks": "None"
            },
            "q06": {
              "choice": "None",
              "remarks": "None"
            },
            "q07": {
              "choice": "None",
              "remarks": "None"
            },
            "q08": {
              "choice": "None",
              "remarks": "None"
            },
            "q09": {
              "choice": "None",
              "remarks": "None"
            },
            "q10": {
              "choice": "None",
              "remarks": "None"
            },
            "q11": {
              "specify": "None"
            }
          }
        },
        "sectionTwo": {
          "assessmentOfControlMeasures": {
            "q01": {
              "choice": "None",
              "remarks": "None"
            },
            "q02": {
              "choice": "None",
              "remarks": "None"
            }
          },
          "siteSurveyFromSupervisor": {
            "q01": {
              "choice": "None",
              "remarks": "None"
            },
            "q02": {
              "choice": "None",
              "remarks": "None"
            }
          },
          "multiLocOrExtentedDuration": {
            "q01": {
              "choice": "None",
              "remarks": "None"
            },
            "q02": {
              "choice": "None",
              "remarks": "None"
            }
          }
        },
        "sectionThree": {
          "permitReview": {
            "q01": {
              "choice": "None",
              "remarks": "None"
            },
            "q02": {
              "choice": "None",
              "remarks": "None"
            },
            "q03": {
              "choice": "None",
              "remarks": "None"
            },
            "q04": {
              "choice": "None",
              "remarks": "None"
            }
          }
        }
      },
      "confinedSpace": {
        "sectionOne": {
          "potentialHazards": {
            "atmo": "None",
            "nonAtmo": "None"
          },
          "controlMeasuresImplemented": {
            "preEntryReqs": {
              "q01": "None",
              "q02": "None",
              "q03": "None",
              "q04": "None",
              "q05": "None",
              "q06": "None",
              "q07": "None",
              "q08": "None"
            },
            "ppe": {
              "q01": "None",
              "q02": "None",
              "q03": "None",
              "q04": "None",
              "q05": "None",
              "q06": "None",
              "q07": {
                "specify": "None"
              }
            }
          }
        },
        "sectionTwo": {
          "gasMonitoringRes": {
            "oxygenLevel": 0,
            "flammableGasLevel": 0,
            "toxicGasLevel": 0,
            "fitForEntry": false
          }
        },
        "sectionThree": {
          "permitReview": {
            "q01": "None",
            "q02": "None",
            "q03": "None",
            "q04": "None"
          }
        }
      },
      "hotWork": {
        "sectionOne": {
          "controlMeasuresImplemented": {
            "q01": {
              "choice": "None",
              "remarks": "None"
            },
            "q02": {
              "choice": "None",
              "remarks": "None"
            },
            "q03": {
              "choice": "None",
              "remarks": "None"
            },
            "q04": {
              "choice": "None",
              "remarks": "None"
            },
            "q05": {
              "choice": "None",
              "remarks": "None"
            },
            "q06": {
              "choice": "None",
              "remarks": "None"
            },
            "q07": {
              "choice": "None",
              "remarks": "None"
            },
            "q08": {
              "choice": "None",
              "remarks": "None"
            },
            "q09": {
              "choice": "None",
              "remarks": "None"
            },
            "q10": {
              "choice": "None",
              "remarks": "None"
            },
            "q11": {
              "choice": "None",
              "remarks": "None"
            },
            "q12": {
              "specify": "None"
            },
            "q13": {
              "specify": "None"
            }
          }
        },
        "sectionTwo": {
          "assessment": {
            "q01": {
              "choice": "None",
              "remarks": "None"
            }
          }
        },
        "sectionThree": {
          "permitReview": {
            "q01": {
              "choice": "None",
              "remarks": "None"
            },
            "q02": {
              "choice": "None",
              "remarks": "None"
            },
            "q03": {
              "choice": "None",
              "remarks": "None"
            },
            "q04": {
              "choice": "None",
              "remarks": "None"
            }
          }
        }
      },
      "coldWork": {
        "sectionOne": {
          "controlMeasuresImplemented": {
            "q01": {
              "choice": "None",
              "remarks": "None"
            },
            "q02": {
              "choice": "None",
              "remarks": "None"
            },
            "q03": {
              "choice": "None",
              "remarks": "None"
            },
            "q04": {
              "choice": "None",
              "remarks": "None"
            },
            "q05": {
              "choice": "None",
              "remarks": "None"
            },
            "q06": {
              "choice": "None",
              "remarks": "None"
            },
            "q07": {
              "choice": "None",
              "remarks": "None"
            },
            "q08": {
              "choice": "None",
              "remarks": "None"
            },
            "q09": {
              "choice": "None",
              "remarks": "None"
            },
            "q10": {
              "specify": "None"
            },
            "q11": {
              "specify": "None"
            }
          }
        },
        "sectionTwo": {
          "assessment": {
            "q01": {
              "choice": "None",
              "remarks": "None"
            }
          }
        },
        "sectionThree": {
          "permitReview": {
            "q01": {
              "choice": "None",
              "remarks": "None"
            },
            "q02": {
              "choice": "None",
              "remarks": "None"
            },
            "q03": {
              "choice": "None",
              "remarks": "None"
            },
            "q04": {
              "choice": "None",
              "remarks": "None"
            }
          }
        }
      },
      "electrical": {
        "sectionOne": {
          "controlMeasuresImplemented": {
            "q01": {
              "choice": "Yes",
              "remarks": "None"
            },
            "q02": {
              "choice": "No",
              "remarks": "None"
            },
            "q03": {
              "choice": "No",
              "remarks": "None"
            },
            "q04": {
              "choice": "No",
              "remarks": "None"
            },
            "q05": {
              "choice": "Yes",
              "remarks": "None"
            },
            "q06": {
              "choice": "No",
              "remarks": "None"
            },
            "q07": {
              "choice": "Yes",
              "remarks": "None"
            },
            "q08": {
              "choice": "Yes",
              "remarks": "None"
            },
            "q09": {
              "choice": "No",
              "remarks": "None"
            },
            "q10": {
              "specify": "None"
            },
            "q11": {
              "specify": "None"
            }
          }
        },
        "sectionTwo": {
          "assessment": {
            "q01": {
              "choice": "None",
              "remarks": "None"
            }
          }
        },
        "sectionThree": {
          "permitReview": {
            "q01": {
              "choice": "None",
              "remarks": "None"
            },
            "q02": {
              "choice": "None",
              "remarks": "None"
            },
            "q03": {
              "choice": "None",
              "remarks": "None"
            },
            "q04": {
              "choice": "None",
              "remarks": "None"
            }
          }
        }
      },
      "attendantDets": [
        {
          "id": 1,
          "name": "John",
          "nricOrFinNo": "F5547646Y",
          "role": "Supervisor",
          "contactNo": "+65 5464-5674"
        },
        {
          "id": 2,
          "name": "Wilson",
          "nricOrFinNo": "D3543653Y",
          "role": "Worker",
          "contactNo": 45365453453
        },
        {
          "id": 3,
          "name": "None",
          "nricOrFinNo": "None",
          "role": "None",
          "contactNo": "None"
        },
        {
          "id": 4,
          "name": "None",
          "nricOrFinNo": "None",
          "role": "None",
          "contactNo": "None"
        },
        {
          "id": 5,
          "name": "None",
          "nricOrFinNo": "None",
          "role": "None",
          "contactNo": "None"
        },
        {
          "id": 6,
          "name": "None",
          "nricOrFinNo": "None",
          "role": "None",
          "contactNo": "None"
        }
      ],
      "applicantDets": {
        "name": "John",
        "nricOrFinNo": "F5547646Y",
        "orgType": "External",
        "orgName": "Elect Org",
        "depName": "Elect Dept",
        "contactNo": "+65 5464-5674",
        "email": "john223@student.tp.edu.sg"
      },
      "ptwStatus": {
        "permitStatus": "Processing",
        "taskStatus": "Not Started",
        "remarks": "None",
        "checked": false,
        "supervisorName": "None",
        "wantToTerminate": false,
        "reqTermTimestamp": "None",
        "terminatedTimestamp": "None",
        "timestamp": "None"
      },
      "safetyAssessorEvaluation": {
        "passed": false,
        "name": "None",
        "timestamp": "None"
      },
      "authorisedManagerApproval": {
        "passed": false,
        "name": "None",
        "timestamp": "None"
      },
      "requestStatus": "Pending",
      "wantToCancel": false,
      "reqCancTimestamp": "None",
      "cancelledTimestamp": "None",
      "timestamp": "2023-06-01T02:32:43.068Z",
      "id": 2
    }
  ]
}